culicidaelab/__init__.py
culicidaelab/serve.py
culicidaelab/conf/config.yaml
culicidaelab/conf/app_settings/development.yaml
culicidaelab/conf/app_settings/production.yaml
culicidaelab/conf/app_settings/testing.yaml
culicidaelab/conf/datasets/classification.yaml
culicidaelab/conf/datasets/detection.yaml
culicidaelab/conf/datasets/segmentation.yaml
culicidaelab/conf/datasets/species_diversity.yaml
culicidaelab/conf/predictors/classifier.yaml
culicidaelab/conf/predictors/detector.yaml
culicidaelab/conf/predictors/segmenter.yaml
culicidaelab/conf/providers/huggingface.yaml
culicidaelab/conf/providers/kaggle.yaml
culicidaelab/conf/providers/roboflow.yaml
culicidaelab/conf/species/species_classes.yaml
culicidaelab/conf/species/species_metadata.yaml
culicidaelab/core/__init__.py
culicidaelab/core/base_inference_backend.py
culicidaelab/core/base_predictor.py
culicidaelab/core/base_provider.py
culicidaelab/core/config_manager.py
culicidaelab/core/config_models.py
culicidaelab/core/prediction_models.py
culicidaelab/core/provider_service.py
culicidaelab/core/resource_manager.py
culicidaelab/core/settings.py
culicidaelab/core/species_config.py
culicidaelab/core/utils.py
culicidaelab/core/weights_manager_protocol.py
culicidaelab/datasets/__init__.py
culicidaelab/datasets/datasets_manager.py
culicidaelab/predictors/__init__.py
culicidaelab/predictors/backend_factory.py
culicidaelab/predictors/classifier.py
culicidaelab/predictors/detector.py
culicidaelab/predictors/model_weights_manager.py
culicidaelab/predictors/segmenter.py
culicidaelab/predictors/backends/__init__.py
culicidaelab/predictors/backends/classifier/_fastai.py
culicidaelab/predictors/backends/classifier/_onnx.py
culicidaelab/predictors/backends/detector/_yolo.py
culicidaelab/predictors/backends/segmenter/_sam.py
culicidaelab/providers/__init__.py
culicidaelab/providers/huggingface_provider.py
culicidaelab-0.3.1.dist-info/licenses/LICENSE
culicidaelab-0.3.1.dist-info/METADATA
culicidaelab-0.3.1.dist-info/WHEEL
culicidaelab-0.3.1.dist-info/top_level.txt
culicidaelab-0.3.1.dist-info/RECORD
