Metadata-Version: 2.4
Name: culicidaelab
Version: 0.3.1
Summary: A Python library for mosquito detection, segmentation, and classification in images
Author-email: Ilona Kovaleva <culicidaelab@gmail.com>
License: AGPL-3.0
Project-URL: Homepage, https://github.com/iloncka/culicidaelab
Project-URL: Repository, https://github.com/iloncka-ds/culicidaelab
Project-URL: Documentation, https://iloncka-ds.github.io/culicidaelab
Project-URL: Bug Tracker, https://github.com/iloncka/culicidaelab/issues
Keywords: mosquito,computer vision,deep learning,classification,detection,segmentation,entomology
Classifier: Development Status :: 4 - Beta
Classifier: Intended Audience :: Developers
Classifier: Intended Audience :: Science/Research
Classifier: License :: OSI Approved :: GNU Affero General Public License v3 or later (AGPLv3+)
Classifier: Operating System :: OS Independent
Classifier: Programming Language :: Python :: 3
Classifier: Programming Language :: Python :: 3.11
Classifier: Topic :: Scientific/Engineering :: Image Recognition
Classifier: Topic :: Scientific/Engineering :: Artificial Intelligence
Classifier: Topic :: Software Development :: Libraries :: Python Modules
Requires-Python: >=3.11
License-File: LICENSE
Requires-Dist: numpy>=1.24.4
Requires-Dist: tqdm>=4.66.1
Requires-Dist: iopath>=0.1.10
Requires-Dist: pillow>=9.4.0
Requires-Dist: pyyaml>=6.0.0
Requires-Dist: huggingface-hub>=0.16.0
Requires-Dist: datasets==4.0.0
Requires-Dist: fastprogress==1.0.3
Requires-Dist: omegaconf>=2.3.0
Requires-Dist: python-dotenv>=0.21.0
Requires-Dist: pycocotools>=2.0.7
Requires-Dist: dill>=0.3.8
Requires-Dist: appdirs>=1.4.4
Requires-Dist: requests>=2.25.1
Requires-Dist: toml>=0.10.2
Requires-Dist: dotenv>=0.9.9
Requires-Dist: pydantic-settings>=2.9.1
Requires-Dist: onnxruntime>=1.22.1
Requires-Dist: matplotlib>=3.10.7
Requires-Dist: scikit-learn>=1.7.2
Provides-Extra: torch
Requires-Dist: torch>=2.3.1; extra == "torch"
Requires-Dist: torchvision>=0.18.1; extra == "torch"
Provides-Extra: gpu-onnx
Requires-Dist: onnxruntime-gpu; extra == "gpu-onnx"
Provides-Extra: serve
Requires-Dist: culicidaelab; extra == "serve"
Provides-Extra: serve-gpu
Requires-Dist: culicidaelab[gpu-onnx]; extra == "serve-gpu"
Provides-Extra: full
Requires-Dist: culicidaelab[torch]; extra == "full"
Requires-Dist: fastai<=2.8.0,>=2.7.0; extra == "full"
Requires-Dist: timm>=0.9.0; extra == "full"
Requires-Dist: ultralytics>=8.3.0; extra == "full"
Provides-Extra: full-gpu
Requires-Dist: culicidaelab[gpu-onnx,torch]; extra == "full-gpu"
Requires-Dist: fastai<=2.8.0,>=2.7.0; extra == "full-gpu"
Requires-Dist: timm>=0.9.0; extra == "full-gpu"
Requires-Dist: ultralytics>=8.3.0; extra == "full-gpu"
Provides-Extra: examples
Requires-Dist: ipykernel==6.16.2; extra == "examples"
Requires-Dist: ipywidgets>=8.1.7; extra == "examples"
Requires-Dist: jupytext>=1.17.2; extra == "examples"
Provides-Extra: docs
Requires-Dist: mkdocs[i18n]>=1.6.1; extra == "docs"
Requires-Dist: mkdocs-material==9.5.46; extra == "docs"
Requires-Dist: mkdocstrings[python]==0.27.0; extra == "docs"
Requires-Dist: mkdocs-custom-fences>=0.1.2; extra == "docs"
Requires-Dist: mkdocs-gallery>=0.10.4; extra == "docs"
Requires-Dist: mike>=2.1.3; extra == "docs"
Provides-Extra: test
Requires-Dist: black==23.3.0; extra == "test"
Requires-Dist: mypy==1.4.1; extra == "test"
Requires-Dist: pre-commit==2.21.0; extra == "test"
Requires-Dist: pytest==7.4.4; extra == "test"
Requires-Dist: pytest-cov==4.1.0; extra == "test"
Requires-Dist: pytest-mock==3.14.1; extra == "test"
Requires-Dist: ruff==0.8.0; extra == "test"
Requires-Dist: twine==5.1.1; extra == "test"
Requires-Dist: bandit==1.8.5; extra == "test"
Requires-Dist: types-requests==2.32.4.20250611; extra == "test"
Requires-Dist: types-pyyaml==6.0.12.20250516; extra == "test"
Requires-Dist: types-toml==0.10.8.20240310; extra == "test"
Requires-Dist: gputil==1.4.0; extra == "test"
Requires-Dist: requests-mock>=1.12.1; extra == "test"
Requires-Dist: tabulate>=0.9.0; extra == "test"
Provides-Extra: dev
Requires-Dist: culicidaelab[docs,examples,full,test]; extra == "dev"
Requires-Dist: pre-commit; extra == "dev"
Dynamic: license-file
